antmiral/__init__.py
antmiral/foo.py
antmiral-0.0.1.dist-info/LICENSE
antmiral-0.0.1.dist-info/METADATA
antmiral-0.0.1.dist-info/WHEEL
antmiral-0.0.1.dist-info/top_level.txt
antmiral-0.0.1.dist-info/RECORD
